ragga/__init__.py
ragga/embedding/__init__.py
ragga/load/__init__.py
ragga/load/chunking.py
ragga/load/extracting.py
ragga/load/load.py
ragga/load/uploading.py
ragga-0.0.2.dist-info/METADATA
ragga-0.0.2.dist-info/WHEEL
ragga-0.0.2.dist-info/RECORD
