Metadata-Version: 2.1
Name: ragga
Version: 0.0.2
Summary: 
Author: Teïlo M
Author-email: teilomillet@gmail.com
Requires-Python: >=3.11,<4.0
Classifier: Programming Language :: Python :: 3
Classifier: Programming Language :: Python :: 3.11
Classifier: Programming Language :: Python :: 3.12
Requires-Dist: llama-index (>=0.10.51,<0.11.0)
